xentropy_cuda_lib.cpython-310-x86_64-linux-gnu.so
xentropy-0.1.2.dist-info/METADATA
xentropy-0.1.2.dist-info/WHEEL
xentropy-0.1.2.dist-info/top_level.txt
xentropy-0.1.2.dist-info/RECORD
