Metadata-Version: 2.1
Name: xentropy
Version: 0.1.2
Summary: Cross-entropy loss
